kac_tools/__init__.py
kac_tools/changelog.py
kac_tools/cli/__init__.py
kac_tools/cli/cli.py
kac_tools-0.4.0.dist-info/LICENSE
kac_tools-0.4.0.dist-info/METADATA
kac_tools-0.4.0.dist-info/WHEEL
kac_tools-0.4.0.dist-info/entry_points.txt
kac_tools-0.4.0.dist-info/top_level.txt
kac_tools-0.4.0.dist-info/RECORD
