Metadata-Version: 2.1
Name: kac-tools
Version: 0.4.0
Summary: Python CLI tool to parse keep-a-changelog formatted files and extract parts.
Author-email: Elias Rosch <eliasrosch@googlemail.com>
License: MIT
Project-URL: Homepage, https://gitlab.com/EvilEli/kac-tools
Project-URL: Documentation, https://gitlab.com/EvilEli/kac-tools
Project-URL: Repository, https://gitlab.com/EvilEli/kac-tools.git
Project-URL: Changelog, https://gitlab.com/EvilEli/kac-tools
Classifier: Programming Language :: Python :: 3
Classifier: License :: OSI Approved :: MIT License
Classifier: Operating System :: OS Independent
Requires-Python: >=3.9
License-File: LICENSE
